{
  "$schema": "https://developer.microsoft.com/json-schemas/fabric/item/report/definition/visualContainer/2.7.0/schema.json",
  "name": "3ce200610401bc857033",
  "position": {
    "x": 569.83646274984858,
    "y": 190.72077528770444,
    "z": 3,
    "height": 298.87341005451242,
    "width": 333.76135675348274
  },
  "visual": {
    "visualType": "cardVisual",
    "query": {
      "queryState": {
        "Data": {
          "projections": [
            {
              "field": {
                "Measure": {
                  "Expression": {
                    "SourceRef": {
                      "Entity": "_Measures"
                    }
                  },
                  "Property": "_Dates_Param"
                }
              },
              "queryRef": "_Measures._Dates_Param",
              "nativeQueryRef": "_Dates_Param"
            }
          ]
        }
      },
      "sortDefinition": {
        "sort": [
          {
            "field": {
              "Measure": {
                "Expression": {
                  "SourceRef": {
                    "Entity": "_Measures"
                  }
                },
                "Property": "_Dates_Param"
              }
            },
            "direction": "Descending"
          }
        ],
        "isDefaultSort": true
      }
    },
    "objects": {
      "value": [
        {
          "properties": {
            "fontSize": {
              "expr": {
                "Literal": {
                  "Value": "20D"
                }
              }
            }
          },
          "selector": {
            "id": "default"
          }
        }
      ],
      "label": [
        {
          "properties": {
            "show": {
              "expr": {
                "Literal": {
                  "Value": "false"
                }
              }
            }
          },
          "selector": {
            "id": "default"
          }
        }
      ],
      "referenceLabel": [
        {
          "properties": {
            "value": {
              "expr": {
                "Measure": {
                  "Expression": {
                    "SourceRef": {
                      "Entity": "_Measures"
                    }
                  },
                  "Property": "_Dates_Param_Delta"
                }
              }
            }
          },
          "selector": {
            "data": [
              {
                "dataViewWildcard": {
                  "matchingOption": 0
                }
              }
            ],
            "metadata": "_Measures._Dates_Param",
            "id": "field-dd4c4b27-6f0b-cd9e-0c1f-b6efffd55282",
            "order": 0
          }
        },
        {
          "properties": {},
          "selector": {
            "data": [
              {
                "dataViewWildcard": {
                  "matchingOption": 0
                }
              }
            ],
            "metadata": "_Measures._Dates_Param",
            "id": "field-c1f5c11d-83a9-318c-c5c2-f35e3d88b49c",
            "order": 1
          }
        }
      ],
      "referenceLabelTitle": [
        {
          "properties": {
            "show": {
              "expr": {
                "Literal": {
                  "Value": "false"
                }
              }
            }
          },
          "selector": {
            "metadata": "_Measures._Dates_Param"
          }
        }
      ],
      "referenceLabelDetail": [
        {
          "properties": {
            "show": {
              "expr": {
                "Literal": {
                  "Value": "true"
                }
              }
            }
          },
          "selector": {
            "metadata": "_Measures._Dates_Param"
          }
        },
        {
          "properties": {
            "detailValue": {
              "expr": {
                "Measure": {
                  "Expression": {
                    "SourceRef": {
                      "Entity": "_Measures"
                    }
                  },
                  "Property": "_PP_Reference_Label"
                }
              }
            },
            "detailFontColor": {
              "solid": {
                "color": {
                  "expr": {
                    "Measure": {
                      "Expression": {
                        "SourceRef": {
                          "Entity": "_Measures"
                        }
                      },
                      "Property": "_Reference_Label_Font_Color"
                    }
                  }
                }
              }
            },
            "detailBackgroundColor": {
              "solid": {
                "color": {
                  "expr": {
                    "Measure": {
                      "Expression": {
                        "SourceRef": {
                          "Entity": "_Measures"
                        }
                      },
                      "Property": "_Reference_Label_Background_Color"
                    }
                  }
                }
              }
            }
          },
          "selector": {
            "data": [
              {
                "dataViewWildcard": {
                  "matchingOption": 0
                }
              }
            ],
            "metadata": "_Measures._Dates_Param",
            "id": "field-dd4c4b27-6f0b-cd9e-0c1f-b6efffd55282"
          }
        },
        {
          "properties": {
            "detailFontSize": {
              "expr": {
                "Literal": {
                  "Value": "12D"
                }
              }
            }
          },
          "selector": {
            "metadata": "_Measures._Dates_Param",
            "id": "field-dd4c4b27-6f0b-cd9e-0c1f-b6efffd55282"
          }
        }
      ],
      "referenceLabelValue": [
        {
          "properties": {
            "show": {
              "expr": {
                "Literal": {
                  "Value": "false"
                }
              }
            }
          },
          "selector": {
            "metadata": "_Measures._Dates_Param",
            "id": "field-dd4c4b27-6f0b-cd9e-0c1f-b6efffd55282"
          }
        }
      ],
      "referenceLabelLayout": [
        {
          "properties": {
            "arrangement": {
              "expr": {
                "Literal": {
                  "Value": "'rows'"
                }
              }
            },
            "position": {
              "expr": {
                "Literal": {
                  "Value": "'right'"
                }
              }
            },
            "verticalAlignment": {
              "expr": {
                "Literal": {
                  "Value": "'middle'"
                }
              }
            },
            "style": {
              "expr": {
                "Literal": {
                  "Value": "'sentence'"
                }
              }
            },
            "horizontalAlignment": {
              "expr": {
                "Literal": {
                  "Value": "'left'"
                }
              }
            }
          },
          "selector": {
            "id": "default"
          }
        }
      ],
      "divider": [
        {
          "properties": {
            "show": {
              "expr": {
                "Literal": {
                  "Value": "true"
                }
              }
            },
            "dividerTransparency": {
              "expr": {
                "Literal": {
                  "Value": "100D"
                }
              }
            }
          },
          "selector": {
            "id": "default"
          }
        }
      ],
      "fillCustom": [
        {
          "properties": {
            "show": {
              "expr": {
                "Literal": {
                  "Value": "false"
                }
              }
            }
          }
        }
      ],
      "outline": [
        {
          "properties": {
            "show": {
              "expr": {
                "Literal": {
                  "Value": "false"
                }
              }
            }
          },
          "selector": {
            "id": "default"
          }
        }
      ]
    },
    "visualContainerObjects": {
      "title": [
        {
          "properties": {
            "text": {
              "expr": {
                "Measure": {
                  "Expression": {
                    "SourceRef": {
                      "Entity": "_Measures"
                    }
                  },
                  "Property": "_Selected_Measure_Text"
                }
              }
            },
            "fontSize": {
              "expr": {
                "Literal": {
                  "Value": "20D"
                }
              }
            }
          }
        }
      ],
      "subTitle": [
        {
          "properties": {
            "show": {
              "expr": {
                "Literal": {
                  "Value": "false"
                }
              }
            }
          }
        }
      ]
    },
    "drillFilterOtherVisuals": true
  },
  "filterConfig": {
    "filters": [
      {
        "name": "19cac683c89b11002723",
        "field": {
          "Measure": {
            "Expression": {
              "SourceRef": {
                "Entity": "_Measures"
              }
            },
            "Property": "_Dates_Param"
          }
        },
        "type": "Advanced"
      }
    ]
  }
}